test/__init__.py
vorpy/__init__.py
vorpy/__main__.py
vorpy/cmd.py
vorpy/api/__init__.py
vorpy/api/GUI/__init__.py
vorpy/api/calculations/__init__.py
vorpy/api/chemistry/__init__.py
vorpy/api/command/__init__.py
vorpy/api/group/__init__.py
vorpy/api/inputs/__init__.py
vorpy/api/interface/__init__.py
vorpy/api/network/__init__.py
vorpy/api/objects/__init__.py
vorpy/api/output/__init__.py
vorpy/api/system/__init__.py
vorpy/api/visualize/__init__.py
vorpy/data/1BNA.pdb
vorpy/data/BSA.pdb
vorpy/data/Cluster.pdb
vorpy/data/DB1976.pdb
vorpy/data/EDTA.pdb
vorpy/data/HO_cube.pdb
vorpy/data/NCP.pdb
vorpy/data/Na5.pdb
vorpy/data/__init__.py
vorpy/data/cambrin.pdb
vorpy/data/foam.pdb
vorpy/data/hairpin.pdb
vorpy/data/hammerhead.pdb
vorpy/data/p53tet.pdb
vorpy/data/streptavidin.pdb
vorpy/data/t4lp.pdb
vorpy/data/VerificationFoams/1.0_0.5_1000_0.05_0.0_gamma_True_False.pdb
vorpy/data/VerificationFoams/1.0_0.5_1000_0.05_0.0_gamma_True_False.txt
vorpy/data/VerificationFoams/1.0_0.5_1000_0.05_0.0_gamma_True_False_1.pdb
vorpy/data/VerificationFoams/1.0_0.5_1000_0.05_0.0_gamma_True_False_1.txt
vorpy/data/VerificationFoams/1.0_0.5_1000_0.05_0.0_gamma_True_False_2.pdb
vorpy/data/VerificationFoams/1.0_0.5_1000_0.05_0.0_gamma_True_False_2.txt
vorpy/data/VerificationFoams/1.0_0.5_1000_0.05_0.0_gamma_True_False_3.pdb
vorpy/data/VerificationFoams/1.0_0.5_1000_0.05_0.0_gamma_True_False_3.txt
vorpy/data/VerificationFoams/1.0_0.5_1000_0.05_1.0_gamma_True_False.pdb
vorpy/data/VerificationFoams/1.0_0.5_1000_0.05_1.0_gamma_True_False.txt
vorpy/data/VerificationFoams/1.0_0.5_1000_0.05_1.0_gamma_True_False_1.pdb
vorpy/data/VerificationFoams/1.0_0.5_1000_0.05_1.0_gamma_True_False_1.txt
vorpy/data/VerificationFoams/1.0_0.5_1000_0.05_1.0_gamma_True_False_2.pdb
vorpy/data/VerificationFoams/1.0_0.5_1000_0.05_1.0_gamma_True_False_2.txt
vorpy/data/VerificationFoams/1.0_0.5_1000_0.05_1.0_gamma_True_False_3.pdb
vorpy/data/VerificationFoams/1.0_0.5_1000_0.05_1.0_gamma_True_False_3.txt
vorpy3-3.1.1.dist-info/licenses/LICENSE
vorpy3-3.1.1.dist-info/METADATA
vorpy3-3.1.1.dist-info/WHEEL
vorpy3-3.1.1.dist-info/entry_points.txt
vorpy3-3.1.1.dist-info/top_level.txt
vorpy3-3.1.1.dist-info/RECORD
